mserv/__init__.py
mserv/mserv.py
mserv-0.8.4.dist-info/entry_points.txt
mserv-0.8.4.dist-info/WHEEL
mserv-0.8.4.dist-info/METADATA
mserv-0.8.4.dist-info/RECORD
