Metadata-Version: 2.1
Name: mserv
Version: 0.8.4
Summary: A simple wrapper for managing your Minecraft servers.
Home-page: https://gitlab.com/mexiquin/mserv
Author: Quinton Jasper
Author-email: dropatuningmetal@gmail.com
Requires-Python: >=3.8,<4.0
Classifier: Programming Language :: Python :: 3
Classifier: Programming Language :: Python :: 3.8
Classifier: Programming Language :: Python :: 3.9
Requires-Dist: beautifulsoup4 (>=4.9.3,<5.0.0)
Requires-Dist: click (>=7.1.2,<8.0.0)
Requires-Dist: requests (>=2.25.0,<3.0.0)
Requires-Dist: rich (>=9.8.0,<10.0.0)
Project-URL: Repository, https://gitlab.com/mexiquin/mserv
